Metadata-Version: 1.0
Name: distributions-spovi
Version: 0.2
Summary: Gaussian distributions
Home-page: UNKNOWN
Author: SPoVi
Author-email: snop.vlc@gmail.com
License: UNKNOWN
Platform: UNKNOWN
